reahl/partymodel.py
reahl/systemaccountmodel.py
reahl/workflowmodel.py
reahl/domain/__init__.py
reahl/domain/migrations.py
reahl/domain/partymodel.py
reahl/domain/systemaccountmodel.py
reahl/domain/workflowmodel.py
reahl/domain_dev/__init__.py
reahl/domain_dev/accounts.puml
reahl/domain_dev/contents.mm
reahl/domain_dev/fixtures.py
reahl/domain_dev/systemaccount_and_party.puml
reahl/domain_dev/test_party.py
reahl/domain_dev/test_workflow.py
reahl/domain_dev/workflow_action_and_requirement.puml
reahl/domain_dev/workflow_inbox.puml
reahl/messages/reahl-domain
reahl/messages/af/LC_MESSAGES/reahl-domain.mo
reahl/messages/af/LC_MESSAGES/reahl-domain.po
reahl_domain-7.0.3.dist-info/LICENSE
reahl_domain-7.0.3.dist-info/METADATA
reahl_domain-7.0.3.dist-info/WHEEL
reahl_domain-7.0.3.dist-info/entry_points.txt
reahl_domain-7.0.3.dist-info/reahl-component.toml
reahl_domain-7.0.3.dist-info/top_level.txt
reahl_domain-7.0.3.dist-info/RECORD
