Metadata-Version: 2.1
Name: reahl-domain
Version: 7.0.3
Summary: End-user domain functionality for use with Reahl.
Author-email: Iwan Vosloo <iwan@reahl.org>, Craig Sparks <craig@reahl.org>
Classifier: Development Status :: 5 - Production/Stable
Classifier: Intended Audience :: Developers
Classifier: License :: OSI Approved
Classifier: Operating System :: OS Independent
Classifier: Programming Language :: Python :: 3
Requires-Python: >=3.8
License-File: LICENSE
Requires-Dist: reahl-component <7.1,>=7.0
Requires-Dist: reahl-mailutil <7.1,>=7.0
Requires-Dist: reahl-sqlalchemysupport <7.1,>=7.0
Requires-Dist: reahl-web-declarative <7.1,>=7.0
Requires-Dist: passlib <1.7.9999,>=1.7.1
Requires-Dist: SQLAlchemy <2.1.999,>=1.4
Provides-Extra: test
Requires-Dist: pytest >=3.0 ; extra == 'test'
Requires-Dist: reahl-tofu ; extra == 'test'
Requires-Dist: reahl-stubble ; extra == 'test'
Requires-Dist: reahl-dev ; extra == 'test'
Requires-Dist: reahl-webdev ; extra == 'test'
Requires-Dist: reahl-browsertools ; extra == 'test'
Requires-Dist: reahl-postgresqlsupport ; extra == 'test'
